openasce/__init__.py
openasce/version.py
openasce/attribution/__init__.py
openasce/attribution/attribution_model.py
openasce/attribution/attribution_test.py
openasce/core/__init__.py
openasce/core/runtime.py
openasce/core/runtime_test.py
openasce/discovery/__init__.py
openasce/discovery/causal_graph.py
openasce/discovery/discovery.py
openasce/discovery/graph_node_form.py
openasce/discovery/regression_discovery/__init__.py
openasce/discovery/regression_discovery/lbfgsb_optimizer.py
openasce/discovery/regression_discovery/locally_connected.py
openasce/discovery/regression_discovery/notears_mlp.py
openasce/discovery/regression_discovery/regression_discovery.py
openasce/discovery/regression_discovery/regression_discovery_test.py
openasce/discovery/regression_discovery/regression_strategy.py
openasce/discovery/regression_discovery/trace_expm.py
openasce/discovery/search_discovery/__init__.py
openasce/discovery/search_discovery/search_discovery.py
openasce/discovery/search_discovery/search_discovery_test.py
openasce/discovery/search_discovery/search_strategy.py
openasce/extension/__init__.py
openasce/extension/debias_model.py
openasce/extension/debias_model_test.py
openasce/extension/debias/__init__.py
openasce/extension/debias/cfr.py
openasce/extension/debias/debias_ips.py
openasce/extension/debias/dice.py
openasce/extension/debias/dmbr.py
openasce/extension/debias/doubly_robust.py
openasce/extension/debias/fairco.py
openasce/extension/debias/ipw.py
openasce/extension/debias/macr.py
openasce/extension/debias/pda.py
openasce/extension/debias/common/__init__.py
openasce/extension/debias/common/utils.py
openasce/inference/__init__.py
openasce/inference/graph_inference.py
openasce/inference/graph_inference_test.py
openasce/inference/inference_model.py
openasce/inference/t_model.py
openasce/inference/learner/__init__.py
openasce/inference/learner/dml.py
openasce/inference/learner/dml_test.py
openasce/inference/learner/drlearner.py
openasce/inference/learner/drlearner_test.py
openasce-0.1.0.dist-info/LICENSE
openasce-0.1.0.dist-info/METADATA
openasce-0.1.0.dist-info/WHEEL
openasce-0.1.0.dist-info/top_level.txt
openasce-0.1.0.dist-info/RECORD
